serve_dir/__init__.py
serve_dir/__main__.py
serve_dir/main.py
serve_dir/segments.py
serve_dir/server.py
serve_dir/utils.py
serve_dir-0.0.3.dist-info/licenses/LICENSE
serve_dir-0.0.3.dist-info/METADATA
serve_dir-0.0.3.dist-info/WHEEL
serve_dir-0.0.3.dist-info/top_level.txt
serve_dir-0.0.3.dist-info/RECORD
