Metadata-Version: 2.4
Name: serve_dir
Version: 0.0.3
Summary: Enhanced HTTP directory server with byte-range support, CGI, and segment handling
Author: Jet-Logic
Project-URL: Homepage, https://github.com/jet-logic/serve_dir
Project-URL: Documentation, https://github.com/jet-logic/serve_dir#readme
Project-URL: BugTracker, https://github.com/jet-logic/serve_dir/issues
Classifier: Development Status :: 4 - Beta
Classifier: Environment :: Web Environment
Classifier: Intended Audience :: Developers
Classifier: Operating System :: OS Independent
Classifier: Programming Language :: Python :: 3
Classifier: Programming Language :: Python :: 3.7
Classifier: Programming Language :: Python :: 3.8
Classifier: Programming Language :: Python :: 3.9
Classifier: Programming Language :: Python :: 3.10
Classifier: Programming Language :: Python :: 3.11
Classifier: Topic :: Internet :: WWW/HTTP :: HTTP Servers
Classifier: Topic :: Utilities
Requires-Python: >=3.7
License-File: LICENSE
Dynamic: license-file
